miritools/__init__.py
miritools/constants.py
miritools/coord.py
miritools/flux.py
miritools/imager.py
miritools/imlib.py
miritools/mask.py
miritools/plot.py
miritools/read.py
miritools/utils.py
miritools/write.py
miritools-4.0.6.dist-info/licenses/LICENCE
miritools-4.0.6.dist-info/METADATA
miritools-4.0.6.dist-info/WHEEL
miritools-4.0.6.dist-info/top_level.txt
miritools-4.0.6.dist-info/RECORD
